relations/__init__.py
relations/field.py
relations/migrations.py
relations/model.py
relations/record.py
relations/relation.py
relations/source.py
relations/titles.py
relations/unittest.py
relations_dil-0.6.13.dist-info/LICENSE.txt
relations_dil-0.6.13.dist-info/METADATA
relations_dil-0.6.13.dist-info/WHEEL
relations_dil-0.6.13.dist-info/top_level.txt
relations_dil-0.6.13.dist-info/RECORD
