Metadata-Version: 2.1
Name: relations-dil
Version: 0.6.13
Home-page: https://github.com/relations-dil/python-relations
Author: Gaffer Fitch
Author-email: relations@gaf3.com
Classifier: Programming Language :: Python :: 3
Classifier: License :: OSI Approved :: MIT License
License-File: LICENSE.txt
Requires-Dist: overscore (==0.1.1)
